immuneML/__init__.py
immuneML/IO/__init__.py
immuneML/IO/dataset_export/AIRRExporter.py
immuneML/IO/dataset_export/DataExporter.py
immuneML/IO/dataset_export/ImmuneMLExporter.py
immuneML/IO/dataset_export/__init__.py
immuneML/IO/dataset_import/AIRRImport.py
immuneML/IO/dataset_import/DataImport.py
immuneML/IO/dataset_import/DatasetImportParams.py
immuneML/IO/dataset_import/GenericImport.py
immuneML/IO/dataset_import/IGoRImport.py
immuneML/IO/dataset_import/IReceptorImport.py
immuneML/IO/dataset_import/ImmuneMLImport.py
immuneML/IO/dataset_import/ImmunoSEQRearrangementImport.py
immuneML/IO/dataset_import/ImmunoSEQSampleImport.py
immuneML/IO/dataset_import/MiXCRImport.py
immuneML/IO/dataset_import/OLGAImport.py
immuneML/IO/dataset_import/RandomReceptorDatasetImport.py
immuneML/IO/dataset_import/RandomRepertoireDatasetImport.py
immuneML/IO/dataset_import/RandomSequenceDatasetImport.py
immuneML/IO/dataset_import/TenxGenomicsImport.py
immuneML/IO/dataset_import/VDJdbImport.py
immuneML/IO/dataset_import/__init__.py
immuneML/IO/dataset_import/conversion/imgt_adaptive_conversion.csv
immuneML/IO/ml_method/MLExporter.py
immuneML/IO/ml_method/MLImport.py
immuneML/IO/ml_method/MLMethodConfiguration.py
immuneML/IO/ml_method/UtilIO.py
immuneML/IO/ml_method/__init__.py
immuneML/analysis/AxisType.py
immuneML/analysis/SequenceMatcher.py
immuneML/analysis/__init__.py
immuneML/analysis/criteria_matches/BooleanType.py
immuneML/analysis/criteria_matches/CriteriaMatcher.py
immuneML/analysis/criteria_matches/CriteriaTypeInstantiator.py
immuneML/analysis/criteria_matches/DataType.py
immuneML/analysis/criteria_matches/OperationType.py
immuneML/analysis/criteria_matches/__init__.py
immuneML/analysis/data_manipulation/DataReshaper.py
immuneML/analysis/data_manipulation/NormalizationType.py
immuneML/analysis/data_manipulation/ReductionMethod.py
immuneML/analysis/data_manipulation/__init__.py
immuneML/analysis/entropy_calculations/EntropyCalculator.py
immuneML_dev-0.0.5.dist-info/LICENSE.md
immuneML_dev-0.0.5.dist-info/METADATA
immuneML_dev-0.0.5.dist-info/WHEEL
immuneML_dev-0.0.5.dist-info/entry_points.txt
immuneML_dev-0.0.5.dist-info/top_level.txt
immuneML_dev-0.0.5.dist-info/RECORD
