Metadata-Version: 2.1
Name: immuneML-dev
Version: 0.0.5
Summary: immuneML is a software platform for machine learning analysis of immune receptor repertoires.
Home-page: https://github.com/uio-bmi/immuneML
Author: immuneML Team
Author-email: milenpa@student.matnat.uio.no
Classifier: Programming Language :: Python :: 3
Classifier: License :: OSI Approved :: GNU Affero General Public License v3
Requires-Python: >=3.7
License-File: LICENSE.md
Requires-Dist: numpy <=1.23.5
Requires-Dist: pytest >=4
Requires-Dist: pandas <2.0,>=1
Requires-Dist: PyYAML >=5.3
Requires-Dist: scikit-learn >=0.23
Requires-Dist: gensim >=4
Requires-Dist: matplotlib >=3.1
Requires-Dist: editdistance
Requires-Dist: regex
Requires-Dist: tzlocal
Requires-Dist: airr <1.4,>=1
Requires-Dist: fishersapi
Requires-Dist: pystache
Requires-Dist: torch >=1.5.1
Requires-Dist: dill >=0.3
Requires-Dist: plotly >=4
Requires-Dist: logomaker >=0.8
Requires-Dist: matplotlib-venn >=0.11
Requires-Dist: scipy
Requires-Dist: bionumpy
Provides-Extra: tcrdist
Requires-Dist: parasail ==1.2 ; extra == 'tcrdist'
Requires-Dist: tcrdist3 >=0.1.6 ; extra == 'tcrdist'
Provides-Extra: gen_models
Requires-Dist: olga ; extra == 'gen_models'
Requires-Dist: sonnia ; extra == 'gen_models'
